tfilterspy/__init__.py
tfilterspy/base_estimator.py
tfilterspy/state_estimation/__init__.py
tfilterspy/state_estimation/linear_filters.py
tfilterspy/state_estimation/nonlinear_filters.py
tfilterspy/state_estimation/particle_filters.py
tfilterspy/utils/__init__.py
tfilterspy/utils/optimisation_utils.py
tfilterspy-1.0.5.dist-info/licenses/LICENSE
tfilterspy-1.0.5.dist-info/METADATA
tfilterspy-1.0.5.dist-info/WHEEL
tfilterspy-1.0.5.dist-info/top_level.txt
tfilterspy-1.0.5.dist-info/RECORD
