Metadata-Version: 2.4
Name: tfilterspy
Version: 1.0.5
Summary: A Python package for state estimation using Kalman and Particle Filters
Home-page: https://github.com/ubunye-ai-ecosystems/tfilterspy
Author: Thabang L. Mashinini-Sekgoto, Lebogang L. Sekgoto, Palesa L. Sekgoto
Author-email: Thabang Mashinini-Sekhoto <thabangline@gmail.com>
License: MIT License
Project-URL: Homepage, https://github.com/ubunye-ai-ecosystems/tfilterspy
Project-URL: Documentation, https://ubunye-ai-ecosystems.github.io/tfilterspy/
Project-URL: Repository, https://github.com/ubunye-ai-ecosystems/tfilterspy.git
Project-URL: Tracker, https://github.com/ubunye-ai-ecosystems/tfilterspy/issues
Requires-Python: >=3.8
License-File: LICENSE
Requires-Dist: numpy>=1.21
Requires-Dist: dask>=2024.8.0
Requires-Dist: scipy>=1.7
Provides-Extra: dev
Requires-Dist: pytest>=7.0; extra == "dev"
Requires-Dist: flake8>=4.0.1; extra == "dev"
Dynamic: author
Dynamic: home-page
Dynamic: license-file
Dynamic: requires-python
